rdjohns_pg/Datatable_Data.py
rdjohns_pg/Datatable_JS.py
rdjohns_pg/InsertComand.py
rdjohns_pg/Str_verification.py
rdjohns_pg/Write_log.py
rdjohns_pg/__init__.py
rdjohns_pg/date.py
rdjohns_pg/rdjohns_pg.py
rdjohns_pg-1.6.5.dist-info/LICENSE
rdjohns_pg-1.6.5.dist-info/METADATA
rdjohns_pg-1.6.5.dist-info/WHEEL
rdjohns_pg-1.6.5.dist-info/top_level.txt
rdjohns_pg-1.6.5.dist-info/RECORD
