Metadata-Version: 2.1
Name: rdjohns-pg
Version: 1.6.5
Summary: Use for the multiple delete, update or insert and select!
Home-page: https://github.com/RDJohns/rdjohns_pg
Author: David Johns
Author-email: rakotonindrianajohns@email.com
Classifier: Programming Language :: Python :: 3
Classifier: License :: OSI Approved :: MIT License
Classifier: Operating System :: OS Independent
License-File: LICENSE
